contigion_charts/__init__.py
contigion_charts/config.py
contigion_charts/main.py
contigion_charts/strategy.py
contigion_charts/components/__init__.py
contigion_charts/components/button.py
contigion_charts/components/container.py
contigion_charts/components/graph.py
contigion_charts/components/input.py
contigion_charts/components/text.py
contigion_charts/dash_app/__init__.py
contigion_charts/dash_app/app.py
contigion_charts/dash_app/pages/__init__.py
contigion_charts/dash_app/pages/home.py
contigion_charts/dash_app/pages/visaualise.py
contigion_charts/util/__init__.py
contigion_charts/util/functions.py
contigion_charts/util/graph.py
contigion_charts/util/indicators.py
contigion_charts-1.0.1.dist-info/METADATA
contigion_charts-1.0.1.dist-info/WHEEL
contigion_charts-1.0.1.dist-info/top_level.txt
contigion_charts-1.0.1.dist-info/RECORD
