Metadata-Version: 2.2
Name: contigion-charts
Version: 1.0.1
Summary: A library for visualising the forex charts
Author-email: Contigion <contigion@gmail.com>
Classifier: Programming Language :: Python :: 3.12
Classifier: Operating System :: OS Independent
Requires-Dist: pandas
Requires-Dist: pandas_ta
Requires-Dist: numpy<2.0.0
Requires-Dist: MetaTrader5
